cc_sdk/__init__.py
cc_sdk/aws_config.py
cc_sdk/cc_store.py
cc_sdk/cc_store_s3.py
cc_sdk/config.py
cc_sdk/constants.py
cc_sdk/data_source.py
cc_sdk/data_store.py
cc_sdk/environment_variables.py
cc_sdk/error.py
cc_sdk/file_data_store.py
cc_sdk/file_data_store_s3.py
cc_sdk/get_object_input.py
cc_sdk/json_encoder.py
cc_sdk/logger.py
cc_sdk/message.py
cc_sdk/object_state.py
cc_sdk/payload.py
cc_sdk/plugin_manager.py
cc_sdk/pull_object_input.py
cc_sdk/put_object_input.py
cc_sdk/seed_set.py
cc_sdk/status.py
cc_sdk/store_type.py
cc_sdk/validators.py
cc_python_sdk-0.0.2.dist-info/LICENSE
cc_python_sdk-0.0.2.dist-info/METADATA
cc_python_sdk-0.0.2.dist-info/WHEEL
cc_python_sdk-0.0.2.dist-info/top_level.txt
cc_python_sdk-0.0.2.dist-info/RECORD
