Metadata-Version: 2.1
Name: cc-python-sdk
Version: 0.0.2
Summary: The Python SDK for developing plugins for Cloud Compute
Author-email: Will Lehman <William.P.Lehman@usace.army.mil>, Brendan Barnes <brendan.barnes@mbakerintl.com>, Thomas Williams <thomas.williams@wsp.com>
Project-URL: Homepage, https://github.com/USACE/cc-python-sdk
Project-URL: Bug Tracker, https://github.com/USACE/cc-python-sdk/issues
Classifier: Programming Language :: Python :: 3
Classifier: License :: OSI Approved :: MIT License
Classifier: Operating System :: OS Independent
Requires-Python: >=3.10
License-File: LICENSE
Requires-Dist: attrs (>=22.2.0)
Requires-Dist: boto3 (>=1.26.93)
